aihelper_akshay/__init__.py
aihelper_akshay/core.py
aihelper_akshay/utils.py
aihelper_akshay-0.1.0.dist-info/METADATA
aihelper_akshay-0.1.0.dist-info/WHEEL
aihelper_akshay-0.1.0.dist-info/top_level.txt
aihelper_akshay-0.1.0.dist-info/RECORD
